[{"line":1,"elements":[{"start_timestamp":"2022-01-24T00:21:52.056Z","before":[{"result":{"duration":997200,"status":"passed"},"match":{"location":"Steps.Hook.InitializeTest()"}}],"line":14,"name":"Access Goibibo and search through flights","description":"","id":"access-goibibo-and-search-through-flights;access-goibibo-and-search-through-flights;;2","after":[{"result":{"duration":578099200,"status":"passed"},"match":{"location":"Steps.Hook.TearDownTest()"}}],"type":"scenario","keyword":"Scenario Outline","steps":[{"result":{"duration":16158233200,"status":"passed"},"line":4,"name":"the user navigates to website homepage using data from spreadsheet row 0","match":{"arguments":[{"val":"0","offset":71}],"location":"Steps.FlightStep.theUserNavigatesToWebsiteHomepage(int)"},"keyword":"Given "},{"result":{"duration":60839200,"status":"passed"},"line":5,"name":"an option from is selected for One-Way, Roundtrip or Multi-City","match":{"location":"Steps.FlightStep.anOptionFromIsSelectedForOneWayOrRoundtrip()"},"keyword":"And "},{"result":{"duration":1823470200,"status":"passed"},"line":6,"name":"a starting and final destination are entered","match":{"location":"Steps.FlightStep.aStartingAndFinalDestinationAreEntered()"},"keyword":"And "},{"result":{"duration":122671100,"status":"passed"},"line":7,"name":"a departure and return date are selected","match":{"location":"Steps.FlightStep.aDepartureAndReturnDateAreSelected()"},"keyword":"And "},{"result":{"duration":325131300,"status":"passed"},"line":8,"name":"the user selects the number of travelers and travel class","match":{"location":"Steps.FlightStep.theUserSelectsTheNumberOfTravelersAndTravelClass()"},"keyword":"And "},{"result":{"duration":1853667500,"status":"passed"},"line":9,"name":"the user selects the Search button","match":{"location":"Steps.FlightStep.theUserSelectsTheSearchButton()"},"keyword":"When "},{"result":{"duration":85769100,"status":"passed"},"line":10,"name":"the flight selection page should be displayed","match":{"location":"Steps.FlightStep.theFlightSelectionPageShouldBeDisplayed()"},"keyword":"Then "},{"result":{"duration":3525814600,"status":"passed"},"line":11,"name":"the fare details should be stored in the spreadsheet","match":{"location":"Steps.FlightStep.theFareDetailsShouldBeStoredInTheSpreadsheet()"},"keyword":"Then "}]},{"start_timestamp":"2022-01-24T00:22:16.631Z","before":[{"result":{"status":"passed"},"match":{"location":"Steps.Hook.InitializeTest()"}}],"line":15,"name":"Access Goibibo and search through flights","description":"","id":"access-goibibo-and-search-through-flights;access-goibibo-and-search-through-flights;;3","after":[{"result":{"duration":580831500,"status":"passed"},"match":{"location":"Steps.Hook.TearDownTest()"}}],"type":"scenario","keyword":"Scenario Outline","steps":[{"result":{"duration":4412239300,"status":"passed"},"line":4,"name":"the user navigates to website homepage using data from spreadsheet row 1","match":{"arguments":[{"val":"1","offset":71}],"location":"Steps.FlightStep.theUserNavigatesToWebsiteHomepage(int)"},"keyword":"Given "},{"result":{"duration":58844500,"status":"passed"},"line":5,"name":"an option from is selected for One-Way, Roundtrip or Multi-City","match":{"location":"Steps.FlightStep.anOptionFromIsSelectedForOneWayOrRoundtrip()"},"keyword":"And "},{"result":{"error_message":"Utility.GoibiboException: Arrival location 1 does not match dataset\r\n\tat Pages.GoibiboHomePage.locations(GoibiboHomePage.java:82)\r\n\tat Steps.FlightStep.aStartingAndFinalDestinationAreEntered(FlightStep.java:56)\r\n\tat ✽.a starting and final destination are entered(file:///C:/Users/Samuel%20Nezic/IdeaProjects/CucumberIAG/src/test/java/Features/Flight.feature:6)\r\n","duration":1347817900,"status":"failed"},"line":6,"name":"a starting and final destination are entered","match":{"location":"Steps.FlightStep.aStartingAndFinalDestinationAreEntered()"},"keyword":"And "},{"result":{"status":"skipped"},"line":7,"name":"a departure and return date are selected","match":{"location":"Steps.FlightStep.aDepartureAndReturnDateAreSelected()"},"keyword":"And "},{"result":{"status":"skipped"},"line":8,"name":"the user selects the number of travelers and travel class","match":{"location":"Steps.FlightStep.theUserSelectsTheNumberOfTravelersAndTravelClass()"},"keyword":"And "},{"result":{"status":"skipped"},"line":9,"name":"the user selects the Search button","match":{"location":"Steps.FlightStep.theUserSelectsTheSearchButton()"},"keyword":"When "},{"result":{"status":"skipped"},"line":10,"name":"the flight selection page should be displayed","match":{"location":"Steps.FlightStep.theFlightSelectionPageShouldBeDisplayed()"},"keyword":"Then "},{"result":{"status":"skipped"},"line":11,"name":"the fare details should be stored in the spreadsheet","match":{"location":"Steps.FlightStep.theFareDetailsShouldBeStoredInTheSpreadsheet()"},"keyword":"Then "}]},{"start_timestamp":"2022-01-24T00:22:23.040Z","before":[{"result":{"status":"passed"},"match":{"location":"Steps.Hook.InitializeTest()"}}],"line":16,"name":"Access Goibibo and search through flights","description":"","id":"access-goibibo-and-search-through-flights;access-goibibo-and-search-through-flights;;4","after":[{"result":{"duration":581489200,"status":"passed"},"match":{"location":"Steps.Hook.TearDownTest()"}}],"type":"scenario","keyword":"Scenario Outline","steps":[{"result":{"duration":4425426900,"status":"passed"},"line":4,"name":"the user navigates to website homepage using data from spreadsheet row 2","match":{"arguments":[{"val":"2","offset":71}],"location":"Steps.FlightStep.theUserNavigatesToWebsiteHomepage(int)"},"keyword":"Given "},{"result":{"duration":63781800,"status":"passed"},"line":5,"name":"an option from is selected for One-Way, Roundtrip or Multi-City","match":{"location":"Steps.FlightStep.anOptionFromIsSelectedForOneWayOrRoundtrip()"},"keyword":"And "},{"result":{"duration":2645513000,"status":"passed"},"line":6,"name":"a starting and final destination are entered","match":{"location":"Steps.FlightStep.aStartingAndFinalDestinationAreEntered()"},"keyword":"And "},{"result":{"duration":321142100,"status":"passed"},"line":7,"name":"a departure and return date are selected","match":{"location":"Steps.FlightStep.aDepartureAndReturnDateAreSelected()"},"keyword":"And "},{"result":{"duration":367018500,"status":"passed"},"line":8,"name":"the user selects the number of travelers and travel class","match":{"location":"Steps.FlightStep.theUserSelectsTheNumberOfTravelersAndTravelClass()"},"keyword":"And "},{"result":{"duration":3271345200,"status":"passed"},"line":9,"name":"the user selects the Search button","match":{"location":"Steps.FlightStep.theUserSelectsTheSearchButton()"},"keyword":"When "},{"result":{"duration":150599300,"status":"passed"},"line":10,"name":"the flight selection page should be displayed","match":{"location":"Steps.FlightStep.theFlightSelectionPageShouldBeDisplayed()"},"keyword":"Then "},{"result":{"duration":3832973200,"status":"passed"},"line":11,"name":"the fare details should be stored in the spreadsheet","match":{"location":"Steps.FlightStep.theFareDetailsShouldBeStoredInTheSpreadsheet()"},"keyword":"Then "}]},{"start_timestamp":"2022-01-24T00:22:38.705Z","before":[{"result":{"status":"passed"},"match":{"location":"Steps.Hook.InitializeTest()"}}],"line":17,"name":"Access Goibibo and search through flights","description":"","id":"access-goibibo-and-search-through-flights;access-goibibo-and-search-through-flights;;5","after":[{"result":{"duration":576726300,"status":"passed"},"match":{"location":"Steps.Hook.TearDownTest()"}}],"type":"scenario","keyword":"Scenario Outline","steps":[{"result":{"duration":4619751000,"status":"passed"},"line":4,"name":"the user navigates to website homepage using data from spreadsheet row 3","match":{"arguments":[{"val":"3","offset":71}],"location":"Steps.FlightStep.theUserNavigatesToWebsiteHomepage(int)"},"keyword":"Given "},{"result":{"duration":62830500,"status":"passed"},"line":5,"name":"an option from is selected for One-Way, Roundtrip or Multi-City","match":{"location":"Steps.FlightStep.anOptionFromIsSelectedForOneWayOrRoundtrip()"},"keyword":"And "},{"result":{"duration":1309149300,"status":"passed"},"line":6,"name":"a starting and final destination are entered","match":{"location":"Steps.FlightStep.aStartingAndFinalDestinationAreEntered()"},"keyword":"And "},{"result":{"duration":100730800,"status":"passed"},"line":7,"name":"a departure and return date are selected","match":{"location":"Steps.FlightStep.aDepartureAndReturnDateAreSelected()"},"keyword":"And "},{"result":{"duration":394992600,"status":"passed"},"line":8,"name":"the user selects the number of travelers and travel class","match":{"location":"Steps.FlightStep.theUserSelectsTheNumberOfTravelersAndTravelClass()"},"keyword":"And "},{"result":{"duration":1400625100,"status":"passed"},"line":9,"name":"the user selects the Search button","match":{"location":"Steps.FlightStep.theUserSelectsTheSearchButton()"},"keyword":"When "},{"result":{"error_message":"Utility.GoibiboException: No flight results\r\n\tat Pages.GoibiboFlightSelection.flightSelection(GoibiboFlightSelection.java:30)\r\n\tat Steps.FlightStep.theFlightSelectionPageShouldBeDisplayed(FlightStep.java:78)\r\n\tat ✽.the flight selection page should be displayed(file:///C:/Users/Samuel%20Nezic/IdeaProjects/CucumberIAG/src/test/java/Features/Flight.feature:10)\r\n","duration":46873700,"status":"failed"},"line":10,"name":"the flight selection page should be displayed","match":{"location":"Steps.FlightStep.theFlightSelectionPageShouldBeDisplayed()"},"keyword":"Then "},{"result":{"status":"skipped"},"line":11,"name":"the fare details should be stored in the spreadsheet","match":{"location":"Steps.FlightStep.theFareDetailsShouldBeStoredInTheSpreadsheet()"},"keyword":"Then "}]},{"start_timestamp":"2022-01-24T00:22:47.220Z","before":[{"result":{"status":"passed"},"match":{"location":"Steps.Hook.InitializeTest()"}}],"line":18,"name":"Access Goibibo and search through flights","description":"","id":"access-goibibo-and-search-through-flights;access-goibibo-and-search-through-flights;;6","after":[{"result":{"duration":581017200,"status":"passed"},"match":{"location":"Steps.Hook.TearDownTest()"}}],"type":"scenario","keyword":"Scenario Outline","steps":[{"result":{"duration":4521318700,"status":"passed"},"line":4,"name":"the user navigates to website homepage using data from spreadsheet row 4","match":{"arguments":[{"val":"4","offset":71}],"location":"Steps.FlightStep.theUserNavigatesToWebsiteHomepage(int)"},"keyword":"Given "},{"result":{"duration":57845600,"status":"passed"},"line":5,"name":"an option from is selected for One-Way, Roundtrip or Multi-City","match":{"location":"Steps.FlightStep.anOptionFromIsSelectedForOneWayOrRoundtrip()"},"keyword":"And "},{"result":{"duration":1294201200,"status":"passed"},"line":6,"name":"a starting and final destination are entered","match":{"location":"Steps.FlightStep.aStartingAndFinalDestinationAreEntered()"},"keyword":"And "},{"result":{"duration":216421600,"status":"passed"},"line":7,"name":"a departure and return date are selected","match":{"location":"Steps.FlightStep.aDepartureAndReturnDateAreSelected()"},"keyword":"And "},{"result":{"duration":321142400,"status":"passed"},"line":8,"name":"the user selects the number of travelers and travel class","match":{"location":"Steps.FlightStep.theUserSelectsTheNumberOfTravelersAndTravelClass()"},"keyword":"And "},{"result":{"duration":1641612200,"status":"passed"},"line":9,"name":"the user selects the Search button","match":{"location":"Steps.FlightStep.theUserSelectsTheSearchButton()"},"keyword":"When "},{"result":{"duration":144613500,"status":"passed"},"line":10,"name":"the flight selection page should be displayed","match":{"location":"Steps.FlightStep.theFlightSelectionPageShouldBeDisplayed()"},"keyword":"Then "},{"result":{"duration":4331824600,"status":"passed"},"line":11,"name":"the fare details should be stored in the spreadsheet","match":{"location":"Steps.FlightStep.theFareDetailsShouldBeStoredInTheSpreadsheet()"},"keyword":"Then "}]},{"start_timestamp":"2022-01-24T00:23:00.334Z","before":[{"result":{"status":"passed"},"match":{"location":"Steps.Hook.InitializeTest()"}}],"line":19,"name":"Access Goibibo and search through flights","description":"","id":"access-goibibo-and-search-through-flights;access-goibibo-and-search-through-flights;;7","after":[{"result":{"duration":586620600,"status":"passed"},"match":{"location":"Steps.Hook.TearDownTest()"}}],"type":"scenario","keyword":"Scenario Outline","steps":[{"result":{"duration":4620436300,"status":"passed"},"line":4,"name":"the user navigates to website homepage using data from spreadsheet row 5","match":{"arguments":[{"val":"5","offset":71}],"location":"Steps.FlightStep.theUserNavigatesToWebsiteHomepage(int)"},"keyword":"Given "},{"result":{"duration":61833100,"status":"passed"},"line":5,"name":"an option from is selected for One-Way, Roundtrip or Multi-City","match":{"location":"Steps.FlightStep.anOptionFromIsSelectedForOneWayOrRoundtrip()"},"keyword":"And "},{"result":{"duration":1909767600,"status":"passed"},"line":6,"name":"a starting and final destination are entered","match":{"location":"Steps.FlightStep.aStartingAndFinalDestinationAreEntered()"},"keyword":"And "},{"result":{"duration":199467900,"status":"passed"},"line":7,"name":"a departure and return date are selected","match":{"location":"Steps.FlightStep.aDepartureAndReturnDateAreSelected()"},"keyword":"And "},{"result":{"duration":306181000,"status":"passed"},"line":8,"name":"the user selects the number of travelers and travel class","match":{"location":"Steps.FlightStep.theUserSelectsTheNumberOfTravelersAndTravelClass()"},"keyword":"And "},{"result":{"duration":3663152700,"status":"passed"},"line":9,"name":"the user selects the Search button","match":{"location":"Steps.FlightStep.theUserSelectsTheSearchButton()"},"keyword":"When "},{"result":{"duration":116688500,"status":"passed"},"line":10,"name":"the flight selection page should be displayed","match":{"location":"Steps.FlightStep.theFlightSelectionPageShouldBeDisplayed()"},"keyword":"Then "},{"result":{"duration":4225934600,"status":"passed"},"line":11,"name":"the fare details should be stored in the spreadsheet","match":{"location":"Steps.FlightStep.theFareDetailsShouldBeStoredInTheSpreadsheet()"},"keyword":"Then "}]},{"start_timestamp":"2022-01-24T00:23:16.029Z","before":[{"result":{"status":"passed"},"match":{"location":"Steps.Hook.InitializeTest()"}}],"line":20,"name":"Access Goibibo and search through flights","description":"","id":"access-goibibo-and-search-through-flights;access-goibibo-and-search-through-flights;;8","after":[{"result":{"duration":578506800,"status":"passed"},"match":{"location":"Steps.Hook.TearDownTest()"}}],"type":"scenario","keyword":"Scenario Outline","steps":[{"result":{"error_message":"Utility.GoibiboException: Row 6 is empty\r\n\tat Pages.GoibiboExcel.<init>(GoibiboExcel.java:39)\r\n\tat Steps.FlightStep.theUserNavigatesToWebsiteHomepage(FlightStep.java:43)\r\n\tat ✽.the user navigates to website homepage using data from spreadsheet row 6(file:///C:/Users/Samuel%20Nezic/IdeaProjects/CucumberIAG/src/test/java/Features/Flight.feature:4)\r\n","duration":4772694600,"status":"failed"},"line":4,"name":"the user navigates to website homepage using data from spreadsheet row 6","match":{"arguments":[{"val":"6","offset":71}],"location":"Steps.FlightStep.theUserNavigatesToWebsiteHomepage(int)"},"keyword":"Given "},{"result":{"status":"skipped"},"line":5,"name":"an option from is selected for One-Way, Roundtrip or Multi-City","match":{"location":"Steps.FlightStep.anOptionFromIsSelectedForOneWayOrRoundtrip()"},"keyword":"And "},{"result":{"status":"skipped"},"line":6,"name":"a starting and final destination are entered","match":{"location":"Steps.FlightStep.aStartingAndFinalDestinationAreEntered()"},"keyword":"And "},{"result":{"status":"skipped"},"line":7,"name":"a departure and return date are selected","match":{"location":"Steps.FlightStep.aDepartureAndReturnDateAreSelected()"},"keyword":"And "},{"result":{"status":"skipped"},"line":8,"name":"the user selects the number of travelers and travel class","match":{"location":"Steps.FlightStep.theUserSelectsTheNumberOfTravelersAndTravelClass()"},"keyword":"And "},{"result":{"status":"skipped"},"line":9,"name":"the user selects the Search button","match":{"location":"Steps.FlightStep.theUserSelectsTheSearchButton()"},"keyword":"When "},{"result":{"status":"skipped"},"line":10,"name":"the flight selection page should be displayed","match":{"location":"Steps.FlightStep.theFlightSelectionPageShouldBeDisplayed()"},"keyword":"Then "},{"result":{"status":"skipped"},"line":11,"name":"the fare details should be stored in the spreadsheet","match":{"location":"Steps.FlightStep.theFareDetailsShouldBeStoredInTheSpreadsheet()"},"keyword":"Then "}]},{"start_timestamp":"2022-01-24T00:23:21.384Z","before":[{"result":{"status":"passed"},"match":{"location":"Steps.Hook.InitializeTest()"}}],"line":21,"name":"Access Goibibo and search through flights","description":"","id":"access-goibibo-and-search-through-flights;access-goibibo-and-search-through-flights;;9","after":[{"result":{"duration":574833900,"status":"passed"},"match":{"location":"Steps.Hook.TearDownTest()"}}],"type":"scenario","keyword":"Scenario Outline","steps":[{"result":{"error_message":"Utility.GoibiboException: Row 7 does not exist\r\n\tat Pages.GoibiboExcel.<init>(GoibiboExcel.java:41)\r\n\tat Steps.FlightStep.theUserNavigatesToWebsiteHomepage(FlightStep.java:43)\r\n\tat ✽.the user navigates to website homepage using data from spreadsheet row 7(file:///C:/Users/Samuel%20Nezic/IdeaProjects/CucumberIAG/src/test/java/Features/Flight.feature:4)\r\n","duration":9353954900,"status":"failed"},"line":4,"name":"the user navigates to website homepage using data from spreadsheet row 7","match":{"arguments":[{"val":"7","offset":71}],"location":"Steps.FlightStep.theUserNavigatesToWebsiteHomepage(int)"},"keyword":"Given "},{"result":{"status":"skipped"},"line":5,"name":"an option from is selected for One-Way, Roundtrip or Multi-City","match":{"location":"Steps.FlightStep.anOptionFromIsSelectedForOneWayOrRoundtrip()"},"keyword":"And "},{"result":{"status":"skipped"},"line":6,"name":"a starting and final destination are entered","match":{"location":"Steps.FlightStep.aStartingAndFinalDestinationAreEntered()"},"keyword":"And "},{"result":{"status":"skipped"},"line":7,"name":"a departure and return date are selected","match":{"location":"Steps.FlightStep.aDepartureAndReturnDateAreSelected()"},"keyword":"And "},{"result":{"status":"skipped"},"line":8,"name":"the user selects the number of travelers and travel class","match":{"location":"Steps.FlightStep.theUserSelectsTheNumberOfTravelersAndTravelClass()"},"keyword":"And "},{"result":{"status":"skipped"},"line":9,"name":"the user selects the Search button","match":{"location":"Steps.FlightStep.theUserSelectsTheSearchButton()"},"keyword":"When "},{"result":{"status":"skipped"},"line":10,"name":"the flight selection page should be displayed","match":{"location":"Steps.FlightStep.theFlightSelectionPageShouldBeDisplayed()"},"keyword":"Then "},{"result":{"status":"skipped"},"line":11,"name":"the fare details should be stored in the spreadsheet","match":{"location":"Steps.FlightStep.theFareDetailsShouldBeStoredInTheSpreadsheet()"},"keyword":"Then "}]},{"start_timestamp":"2022-01-24T00:23:31.321Z","before":[{"result":{"duration":996300,"status":"passed"},"match":{"location":"Steps.Hook.InitializeTest()"}}],"line":22,"name":"Access Goibibo and search through flights","description":"","id":"access-goibibo-and-search-through-flights;access-goibibo-and-search-through-flights;;10","after":[{"result":{"duration":569586800,"status":"passed"},"match":{"location":"Steps.Hook.TearDownTest()"}}],"type":"scenario","keyword":"Scenario Outline","steps":[{"result":{"error_message":"Utility.GoibiboException: Row 8 does not exist\r\n\tat Pages.GoibiboExcel.<init>(GoibiboExcel.java:41)\r\n\tat Steps.FlightStep.theUserNavigatesToWebsiteHomepage(FlightStep.java:43)\r\n\tat ✽.the user navigates to website homepage using data from spreadsheet row 8(file:///C:/Users/Samuel%20Nezic/IdeaProjects/CucumberIAG/src/test/java/Features/Flight.feature:4)\r\n","duration":4523273200,"status":"failed"},"line":4,"name":"the user navigates to website homepage using data from spreadsheet row 8","match":{"arguments":[{"val":"8","offset":71}],"location":"Steps.FlightStep.theUserNavigatesToWebsiteHomepage(int)"},"keyword":"Given "},{"result":{"status":"skipped"},"line":5,"name":"an option from is selected for One-Way, Roundtrip or Multi-City","match":{"location":"Steps.FlightStep.anOptionFromIsSelectedForOneWayOrRoundtrip()"},"keyword":"And "},{"result":{"status":"skipped"},"line":6,"name":"a starting and final destination are entered","match":{"location":"Steps.FlightStep.aStartingAndFinalDestinationAreEntered()"},"keyword":"And "},{"result":{"status":"skipped"},"line":7,"name":"a departure and return date are selected","match":{"location":"Steps.FlightStep.aDepartureAndReturnDateAreSelected()"},"keyword":"And "},{"result":{"status":"skipped"},"line":8,"name":"the user selects the number of travelers and travel class","match":{"location":"Steps.FlightStep.theUserSelectsTheNumberOfTravelersAndTravelClass()"},"keyword":"And "},{"result":{"status":"skipped"},"line":9,"name":"the user selects the Search button","match":{"location":"Steps.FlightStep.theUserSelectsTheSearchButton()"},"keyword":"When "},{"result":{"status":"skipped"},"line":10,"name":"the flight selection page should be displayed","match":{"location":"Steps.FlightStep.theFlightSelectionPageShouldBeDisplayed()"},"keyword":"Then "},{"result":{"status":"skipped"},"line":11,"name":"the fare details should be stored in the spreadsheet","match":{"location":"Steps.FlightStep.theFareDetailsShouldBeStoredInTheSpreadsheet()"},"keyword":"Then "}]},{"start_timestamp":"2022-01-24T00:23:36.418Z","before":[{"result":{"status":"passed"},"match":{"location":"Steps.Hook.InitializeTest()"}}],"line":23,"name":"Access Goibibo and search through flights","description":"","id":"access-goibibo-and-search-through-flights;access-goibibo-and-search-through-flights;;11","after":[{"result":{"duration":568867400,"status":"passed"},"match":{"location":"Steps.Hook.TearDownTest()"}}],"type":"scenario","keyword":"Scenario Outline","steps":[{"result":{"error_message":"Utility.GoibiboException: Row 9 does not exist\r\n\tat Pages.GoibiboExcel.<init>(GoibiboExcel.java:41)\r\n\tat Steps.FlightStep.theUserNavigatesToWebsiteHomepage(FlightStep.java:43)\r\n\tat ✽.the user navigates to website homepage using data from spreadsheet row 9(file:///C:/Users/Samuel%20Nezic/IdeaProjects/CucumberIAG/src/test/java/Features/Flight.feature:4)\r\n","duration":24397067100,"status":"failed"},"line":4,"name":"the user navigates to website homepage using data from spreadsheet row 9","match":{"arguments":[{"val":"9","offset":71}],"location":"Steps.FlightStep.theUserNavigatesToWebsiteHomepage(int)"},"keyword":"Given "},{"result":{"status":"skipped"},"line":5,"name":"an option from is selected for One-Way, Roundtrip or Multi-City","match":{"location":"Steps.FlightStep.anOptionFromIsSelectedForOneWayOrRoundtrip()"},"keyword":"And "},{"result":{"status":"skipped"},"line":6,"name":"a starting and final destination are entered","match":{"location":"Steps.FlightStep.aStartingAndFinalDestinationAreEntered()"},"keyword":"And "},{"result":{"status":"skipped"},"line":7,"name":"a departure and return date are selected","match":{"location":"Steps.FlightStep.aDepartureAndReturnDateAreSelected()"},"keyword":"And "},{"result":{"status":"skipped"},"line":8,"name":"the user selects the number of travelers and travel class","match":{"location":"Steps.FlightStep.theUserSelectsTheNumberOfTravelersAndTravelClass()"},"keyword":"And "},{"result":{"status":"skipped"},"line":9,"name":"the user selects the Search button","match":{"location":"Steps.FlightStep.theUserSelectsTheSearchButton()"},"keyword":"When "},{"result":{"status":"skipped"},"line":10,"name":"the flight selection page should be displayed","match":{"location":"Steps.FlightStep.theFlightSelectionPageShouldBeDisplayed()"},"keyword":"Then "},{"result":{"status":"skipped"},"line":11,"name":"the fare details should be stored in the spreadsheet","match":{"location":"Steps.FlightStep.theFareDetailsShouldBeStoredInTheSpreadsheet()"},"keyword":"Then "}]}],"name":"Access Goibibo and search through flights","description":"","id":"access-goibibo-and-search-through-flights","keyword":"Feature","uri":"file:src/test/java/Features/Flight.feature","tags":[]}]